file/__init__.py
neo_file-0.0.1.dist-info/METADATA
neo_file-0.0.1.dist-info/WHEEL
neo_file-0.0.1.dist-info/top_level.txt
neo_file-0.0.1.dist-info/RECORD
