Metadata-Version: 2.1
Name: neo-file
Version: 0.0.1
Summary: An easy to use file tool
Home-page: https://file.justneo.org
Author: Panos
Author-email: wp970601@163.com
License: UNKNOWN
Platform: UNKNOWN
